cinterop/__init__.py
cinterop/_version.py
cinterop/cffi/__init__.py
cinterop/cffi/marshal.py
cinterop/timeseries.py
cinterop-1.0.0.dist-info/LICENSE.txt
cinterop-1.0.0.dist-info/METADATA
cinterop-1.0.0.dist-info/WHEEL
cinterop-1.0.0.dist-info/RECORD
