Metadata-Version: 2.1
Name: cinterop
Version: 1.0.0
Summary: Python classes for C interop via cffi
License: LICENSE.txt
Author: J-M
Author-email: jean-michel.perraud@csiro.au
Requires-Python: >=3.7,<4.0
Classifier: License :: Other/Proprietary License
Classifier: Programming Language :: Python :: 3
Classifier: Programming Language :: Python :: 3.7
Classifier: Programming Language :: Python :: 3.8
Classifier: Programming Language :: Python :: 3.9
Classifier: Programming Language :: Python :: 3.10
Classifier: Programming Language :: Python :: 3.11
Classifier: Programming Language :: Python :: 3.12
Requires-Dist: cffi (>=1.11.5,<2.0.0)
Requires-Dist: refcount (>=1.0.0,<2.0.0)
